django_modern_form_utils-2.0.1.dist-info/licenses/AUTHORS.rst
django_modern_form_utils-2.0.1.dist-info/licenses/LICENSE.txt
modern_form_utils/__init__.py
modern_form_utils/admin.py
modern_form_utils/fields.py
modern_form_utils/forms.py
modern_form_utils/models.py
modern_form_utils/settings.py
modern_form_utils/utils.py
modern_form_utils/widgets.py
modern_form_utils/templates/form_utils/better_form.html
modern_form_utils/templates/form_utils/fields_as_lis.html
modern_form_utils/templates/form_utils/form.html
modern_form_utils/templates/forms/_label.html
modern_form_utils/templatetags/__init__.py
modern_form_utils/templatetags/form_utils.py
django_modern_form_utils-2.0.1.dist-info/METADATA
django_modern_form_utils-2.0.1.dist-info/WHEEL
django_modern_form_utils-2.0.1.dist-info/top_level.txt
django_modern_form_utils-2.0.1.dist-info/RECORD
