Metadata-Version: 2.4
Name: django-modern-form-utils
Version: 2.0.1
Summary: Modernized form utilities for Django 3.2–5.2+
Home-page: https://github.com/yourusername/django-modern-form-utils
Author: Muhammad Ziauldin
Author-email: Muhammad Ziauldin <ziauldin@nexgsol.com>
License: BSD-3-Clause
Project-URL: Homepage, https://github.com/Nexgsol/django-modern-form-utils
Project-URL: Source, https://github.com/Nexgsol/django-modern-form-utils
Project-URL: Issues, https://github.com/Nexgsol/django-modern-form-utils/issues
Classifier: Development Status :: 5 - Production/Stable
Classifier: Environment :: Web Environment
Classifier: Framework :: Django
Classifier: Framework :: Django :: 3.2
Classifier: Framework :: Django :: 4.2
Classifier: Framework :: Django :: 5.0
Classifier: Framework :: Django :: 5.2
Classifier: Intended Audience :: Developers
Classifier: License :: OSI Approved :: BSD License
Classifier: Operating System :: OS Independent
Classifier: Programming Language :: Python :: 3
Classifier: Programming Language :: Python :: 3.8
Classifier: Programming Language :: Python :: 3.9
Classifier: Programming Language :: Python :: 3.10
Classifier: Programming Language :: Python :: 3.11
Classifier: Programming Language :: Python :: 3.12
Classifier: Topic :: Software Development :: Libraries :: Python Modules
Requires-Python: >=3.8
License-File: LICENSE.txt
License-File: AUTHORS.rst
Requires-Dist: Django>=3.2
Requires-Dist: Pillow>=7.0
Provides-Extra: tests
Requires-Dist: Django>=3.2; extra == "tests"
Requires-Dist: mock; extra == "tests"
Requires-Dist: Pillow; extra == "tests"
Dynamic: author
Dynamic: home-page
Dynamic: license-file
Dynamic: requires-python
